pdm_pypi/__init__.py
pdm_pypi/test_class.py
pdm_pypi-0.1.2.dist-info/METADATA
pdm_pypi-0.1.2.dist-info/WHEEL
pdm_pypi-0.1.2.dist-info/RECORD
